invisibleroads_users/__init__.py
invisibleroads_users/constants.py
invisibleroads_users/events.py
invisibleroads_users/models.py
invisibleroads_users/providers.py
invisibleroads_users/routes.py
invisibleroads_users/routines.py
invisibleroads_users/services.py
invisibleroads_users/tests.py
invisibleroads_users/views.py
invisibleroads_users-0.6.4.3.dist-info/METADATA
invisibleroads_users-0.6.4.3.dist-info/WHEEL
invisibleroads_users-0.6.4.3.dist-info/entry_points.txt
invisibleroads_users-0.6.4.3.dist-info/top_level.txt
invisibleroads_users-0.6.4.3.dist-info/zip-safe
invisibleroads_users-0.6.4.3.dist-info/RECORD
