Metadata-Version: 2.1
Name: invisibleroads-users
Version: 0.6.4.3
Summary: Web application security defaults
Home-page: https://github.com/invisibleroads/invisibleroads-users
Author: Roy Hyunjin Han
Author-email: rhh@crosscompute.com
License: UNKNOWN
Keywords: web wsgi bfg pylons pyramid invisibleroads
Platform: UNKNOWN
Classifier: Programming Language :: Python
Classifier: Framework :: Pyramid
Classifier: Topic :: Internet :: WWW/HTTP
Classifier: Topic :: Internet :: WWW/HTTP :: WSGI :: Application
Classifier: License :: OSI Approved :: MIT License
Requires-Dist: pyramid
Requires-Dist: redis
Requires-Dist: sqlalchemy
Requires-Dist: invisibleroads-posts (>=0.7.16.3)
Requires-Dist: invisibleroads-records (>=0.5.9.3)
Requires-Dist: miscreant
Requires-Dist: pyramid-authsanity
Requires-Dist: pyramid-redis-sessions
Requires-Dist: requests-oauthlib
Requires-Dist: invisibleroads-macros-configuration (>=1.0.8)
Requires-Dist: invisibleroads-macros-log (>=1.0.3)
Requires-Dist: invisibleroads-macros-security (>=1.0.1)
Provides-Extra: test
Requires-Dist: pytest-cov ; extra == 'test'
